bracketcreate_pig/__init__.py
bracketcreate_pig/cb.py
bracketcreate_pig-0.0.3.dist-info/METADATA
bracketcreate_pig-0.0.3.dist-info/WHEEL
bracketcreate_pig-0.0.3.dist-info/licenses/LICENSE.txt
bracketcreate_pig-0.0.3.dist-info/RECORD
