Metadata-Version: 2.1
Name: bracketcreate_pig
Version: 0.0.3
Summary: Challonge bracket creator using selenium
Author-email: pig <jharvey9261@gmail.com>
License-File: LICENSE.txt
Classifier: License :: OSI Approved :: MIT License
Classifier: Operating System :: OS Independent
Classifier: Programming Language :: Python :: 3
Requires-Python: >=3.8
